lnmmeshio/__init__.py
lnmmeshio/discretization.py
lnmmeshio/ensightio.py
lnmmeshio/fiber.py
lnmmeshio/ioutils.py
lnmmeshio/meshio_to_discretization.py
lnmmeshio/mimics_stlio.py
lnmmeshio/node.py
lnmmeshio/nodeset.py
lnmmeshio/element/__init__.py
lnmmeshio/element/element.py
lnmmeshio/element/element_container.py
lnmmeshio/element/hex20.py
lnmmeshio/element/hex27.py
lnmmeshio/element/hex8.py
lnmmeshio/element/line2.py
lnmmeshio/element/line3.py
lnmmeshio/element/parse_element.py
lnmmeshio/element/pyramid5.py
lnmmeshio/element/quad4.py
lnmmeshio/element/quad8.py
lnmmeshio/element/quad9.py
lnmmeshio/element/tet10.py
lnmmeshio/element/tet4.py
lnmmeshio/element/tri3.py
lnmmeshio/element/tri6.py
lnmmeshio/element/vertex.py
lnmmeshio/element/wedge6.py
lnmmeshio-5.6.4.dist-info/METADATA
lnmmeshio-5.6.4.dist-info/WHEEL
lnmmeshio-5.6.4.dist-info/licenses/LICENSE
lnmmeshio-5.6.4.dist-info/RECORD
