Metadata-Version: 2.4
Name: lnmmeshio
Version: 5.6.4
Summary: Import and export from and to various mesh formats including dat files
Project-URL: Homepage, https://github.com/amgebauer/lnmmeshio
Project-URL: Bug Tracker, https://github.com/amgebauer/lnmmeshio/issues
Author-email: Amadeus Gebauer <amadeus.gebauer@tum.de>
License-File: LICENSE
Classifier: License :: OSI Approved :: MIT License
Classifier: Operating System :: OS Independent
Classifier: Programming Language :: Python :: 3
Requires-Python: >=3.9
Requires-Dist: loguru>=0.7.2
Requires-Dist: meshio<6,>=5.3.5
Requires-Dist: numpy>=1.26.4
Requires-Dist: python-utils>=2.3.0
Requires-Dist: pyyaml<7,>=6.0.0
Requires-Dist: tqdm==4.66.5
